Metadata-Version: 2.4
Name: middleware-io
Version: 2.4.1
Summary: Middleware's APM tool enables Python developers to effortlessly monitor their applications, gathering distributed tracing, metrics, logs, and profiling data for valuable insights and performance optimization.
Author: middleware-dev
Maintainer: middleware-dev
License: Apache-2.0
Project-URL: Source, https://github.com/middleware-labs/agent-apm-python.git
Project-URL: Homepage, https://docs.middleware.io/docs/apm-configuration/python
Keywords: APM,middleware,monitoring,tracing,metrics,logs
Requires-Python: >=3.8
License-File: LICENSE
Requires-Dist: distro==1.9.0
Requires-Dist: opentelemetry-api==1.36.0
Requires-Dist: opentelemetry-exporter-otlp-proto-grpc==1.36.0
Requires-Dist: opentelemetry-instrumentation==0.57b0
Requires-Dist: opentelemetry-proto==1.36.0
Requires-Dist: opentelemetry-sdk==1.36.0
Requires-Dist: opentelemetry-semantic-conventions==0.57b0
Requires-Dist: opentelemetry-util-http==0.57b0
Requires-Dist: requests==2.32.3
Requires-Dist: psutil==6.0.0
Requires-Dist: opentelemetry-processor-baggage==0.57b0
Requires-Dist: opentelemetry-propagator-b3==1.36.0
Requires-Dist: opentelemetry-propagator-jaeger==1.36.0
Requires-Dist: opentelemetry-propagator-aws-xray==1.0.2
Requires-Dist: opentelemetry-propagator-ot-trace==0.57b0
Requires-Dist: opentelemetry-propagator-gcp==1.9.0
Requires-Dist: opentelemetry-sdk-extension-aws==2.0.2
Requires-Dist: opentelemetry-resource-detector-azure==0.1.5
Requires-Dist: opentelemetry-resourcedetector-gcp==1.9.0a0
Requires-Dist: opentelemetry-resourcedetector-docker==0.4.0
Requires-Dist: gitpython>=3.1.0
Requires-Dist: opentelemetry-instrumentation-aio-pika==0.57b0
Requires-Dist: opentelemetry-instrumentation-aiohttp-client==0.57b0
Requires-Dist: opentelemetry-instrumentation-aiohttp-server==0.57b0
Requires-Dist: opentelemetry-instrumentation-aiokafka==0.57b0
Requires-Dist: opentelemetry-instrumentation-aiopg==0.57b0
Requires-Dist: opentelemetry-instrumentation-asgi==0.57b0
Requires-Dist: opentelemetry-instrumentation-asyncclick==0.57b0
Requires-Dist: opentelemetry-instrumentation-asyncio==0.57b0
Requires-Dist: opentelemetry-instrumentation-asyncpg==0.57b0
Requires-Dist: opentelemetry-instrumentation-aws-lambda==0.57b0
Requires-Dist: opentelemetry-instrumentation-boto==0.57b0
Requires-Dist: opentelemetry-instrumentation-boto3sqs==0.57b0
Requires-Dist: opentelemetry-instrumentation-botocore==0.57b0
Requires-Dist: opentelemetry-instrumentation-cassandra==0.57b0
Requires-Dist: opentelemetry-instrumentation-celery==0.57b0
Requires-Dist: opentelemetry-instrumentation-click==0.57b0
Requires-Dist: opentelemetry-instrumentation-confluent-kafka==0.57b0
Requires-Dist: opentelemetry-instrumentation-dbapi==0.57b0
Requires-Dist: opentelemetry-instrumentation-django==0.57b0
Requires-Dist: opentelemetry-instrumentation-elasticsearch==0.57b0
Requires-Dist: opentelemetry-instrumentation-falcon==0.57b0
Requires-Dist: opentelemetry-instrumentation-fastapi==0.57b0
Requires-Dist: opentelemetry-instrumentation-flask==0.57b0
Requires-Dist: opentelemetry-instrumentation-grpc==0.57b0
Requires-Dist: opentelemetry-instrumentation-httpx==0.57b0
Requires-Dist: opentelemetry-instrumentation-jinja2==0.57b0
Requires-Dist: opentelemetry-instrumentation-kafka-python==0.57b0
Requires-Dist: opentelemetry-instrumentation-logging==0.57b0
Requires-Dist: opentelemetry-instrumentation-mysql==0.57b0
Requires-Dist: opentelemetry-instrumentation-mysqlclient==0.57b0
Requires-Dist: opentelemetry-instrumentation-pika==0.57b0
Requires-Dist: opentelemetry-instrumentation-psycopg==0.57b0
Requires-Dist: opentelemetry-instrumentation-psycopg2==0.57b0
Requires-Dist: opentelemetry-instrumentation-pymemcache==0.57b0
Requires-Dist: opentelemetry-instrumentation-pymongo==0.57b0
Requires-Dist: opentelemetry-instrumentation-pymysql==0.57b0
Requires-Dist: opentelemetry-instrumentation-pymssql==0.57b0
Requires-Dist: opentelemetry-instrumentation-pyramid==0.57b0
Requires-Dist: opentelemetry-instrumentation-redis==0.57b0
Requires-Dist: opentelemetry-instrumentation-remoulade==0.57b0
Requires-Dist: opentelemetry-instrumentation-requests==0.57b0
Requires-Dist: opentelemetry-instrumentation-sqlalchemy==0.57b0
Requires-Dist: opentelemetry-instrumentation-sqlite3==0.57b0
Requires-Dist: opentelemetry-instrumentation-starlette==0.57b0
Requires-Dist: opentelemetry-instrumentation-system-metrics==0.57b0
Requires-Dist: opentelemetry-instrumentation-threading==0.57b0
Requires-Dist: opentelemetry-instrumentation-tornado==0.57b0
Requires-Dist: opentelemetry-instrumentation-tortoiseorm==0.57b0
Requires-Dist: opentelemetry-instrumentation-urllib==0.57b0
Requires-Dist: opentelemetry-instrumentation-urllib3==0.57b0
Requires-Dist: opentelemetry-instrumentation-wsgi
Provides-Extra: profiling
Requires-Dist: pyroscope-io==0.8.5; sys_platform != "win32" and extra == "profiling"
Dynamic: license-file
